py_real_esrgan/__init__.py
py_real_esrgan/__main__.py
py_real_esrgan/arch_utils.py
py_real_esrgan/model.py
py_real_esrgan/rrdbnet_arch.py
py_real_esrgan/utils.py
py_real_esrgan-2.0.0.dist-info/METADATA
py_real_esrgan-2.0.0.dist-info/WHEEL
py_real_esrgan-2.0.0.dist-info/entry_points.txt
py_real_esrgan-2.0.0.dist-info/licenses/LICENSE
py_real_esrgan-2.0.0.dist-info/RECORD
