Metadata-Version: 2.3
Name: py-real-esrgan
Version: 2.0.0
Project-URL: Homepage, https://github.com/ai-forever/Real-ESRGAN
Project-URL: Documentation, https://github.com/ai-forever/Real-ESRGAN/wiki
Project-URL: Repository, https://github.com/ai-forever/Real-ESRGAN.git
Project-URL: Issues, https://github.com/ai-forever/Real-ESRGAN/issues
Project-URL: Changelog, https://github.com/ai-forever/Real-ESRGAN/blob/main/CHANGELOG.md
Author: Sberbank AI, Xintao Wang
Maintainer: Sberbank AI, Xintao Wang, nbdy
License: BSD 3-Clause License
License-File: LICENSE
Classifier: Development Status :: 4 - Beta
Classifier: Programming Language :: Python :: 3.10
Classifier: Programming Language :: Python :: 3.11
Classifier: Programming Language :: Python :: 3.12
Requires-Python: >=3.10
Requires-Dist: huggingface-hub
Requires-Dist: numpy
Requires-Dist: opencv-python
Requires-Dist: pillow
Requires-Dist: torch>=1.7
Requires-Dist: torchvision>=0.8.0
Requires-Dist: tqdm
